{
  "sorted_middleware": [],
  "middleware": {
    "/": {
      "files": [
        "server/edge/chunks/_05c6c43e._.js",
        "server/edge/chunks/[root-of-the-server]__dc15d093._.js",
        "server/edge/chunks/edge-wrapper_bd0b1ca2.js"
      ],
      "name": "middleware",
      "page": "/",
      "matchers": [
        {
          "regexp": "/:nextData(_next/data/[^/]{1,})?/((?!_next/static|_next/image|favicon.ico|api/webhooks|login|register|onboarding|pricing|.*\\.(?:svg|png|jpg|jpeg|gif|webp)$).*){(\\\\.json)}?",
          "originalSource": "/((?!_next/static|_next/image|favicon.ico|api/webhooks|login|register|onboarding|pricing|.*\\.(?:svg|png|jpg|jpeg|gif|webp)$).*)"
        }
      ],
      "wasm": [],
      "assets": [],
      "env": {
        "__NEXT_BUILD_ID": "development",
        "NEXT_SERVER_ACTIONS_ENCRYPTION_KEY": "9OT3PpT6K91QxIHRefd2PTf7b4EMdMEOKyw/128+zKk=",
        "__NEXT_PREVIEW_MODE_ID": "1910202a5ba6a7bde649aa4669e1bb0f",
        "__NEXT_PREVIEW_MODE_ENCRYPTION_KEY": "5ae4c2d484972c2559bd7c98e543fbf9bf731027756040794a6833ac16957e71",
        "__NEXT_PREVIEW_MODE_SIGNING_KEY": "94a15aabf9b9c31c835ca8e9822b13db25713ce7ab0110b8f42c3e411082b967"
      }
    }
  },
  "instrumentation": null,
  "functions": {}
}